{
    "Employees" : [

    {
    "id":"1",
    "jobTitleName":"Developer",
    "firstName":"Romin",
    "lastName":"Irani",
    "preferredFullName":"Romin Irani",
    "region":"CA",
    "phoneNumber":"408-1234567",
    "emailAddress":"romin.k.irani@gmail.com"
    },

    {
    "id":"2",
    "jobTitleName":"Developer",
    "firstName":"Neil",
    "lastName":"Irani",
    "preferredFullName":"Neil Irani",
    "region":"CA",
    "phoneNumber":"408-1111111",
    "emailAddress":"neilrirani@gmail.com"
    },

    {
    "id":"3",
    "jobTitleName":"Program Directory",
    "firstName":"Tom",
    "lastName":"Hanks",
    "preferredFullName":"Tom Hanks",
    "region":"CA",
    "phoneNumber":"408-2222222",
    "emailAddress":"tomhanks@gmail.com"
    },

    {
        "id":"4",
        "jobTitleName":"Full Stack Developer",
        "firstName":"Ahmed",
        "lastName":"Yousef",
        "preferredFullName":"Ahmed Yousef",
        "region":"IS",
        "phoneNumber":"408-2222222",
        "emailAddress":"Ahmed_Yousef@gmail.com"
    }, 
    {
        "id":"5",
        "jobTitleName":"Full Stack Developer",
        "firstName":"Esraa",
        "lastName":"Ayoub",
        "preferredFullName":"Esraa Ayoub",
        "region":"IS",
        "phoneNumber":"408-2222222",
        "emailAddress":"esraaAyoub@gmail.com"
    }, 

    {
        "id":"6",
        "jobTitleName":"Full Stack Developer",
        "firstName":"Thaier",
        "lastName":"Bashir",
        "preferredFullName":"Thaier Bashir",
        "region":"IS",
        "phoneNumber":"408-2222222",
        "emailAddress":"Thaier.Bashir@gmail.com"
    },

    {
        "id":"7",
        "jobTitleName":"Full Stack Developer",
        "firstName":"Doaa",
        "lastName":"Ziadat",
        "preferredFullName":"Doaa Ziadat",
        "region":"IS",
        "phoneNumber":"408-2222222",
        "emailAddress":"doaaziadat@gmail.com"
    },

    {
        "id":"8",
        "jobTitleName":"Backend Engineer",
        "firstName":"Jason",
        "lastName":"Butto",
        "preferredFullName":"Jason Butto",
        "region":"IS",
        "phoneNumber":"408-2222222",
        "emailAddress":"jasonButto@gmail.com"
    },
    
    {
        "id":"9",
        "jobTitleName":"QA Engineer",
        "firstName":"Jerry",
        "lastName":"Reto",
        "preferredFullName":"Jerry Reto",
        "region":"IS",
        "phoneNumber":"408-2222222",
        "emailAddress":"jasonButto@gmail.com"
    },
    
    {
        "id":"10",
        "jobTitleName":"Devops Developr",
        "firstName":"Jacob",
        "lastName":"Bery",
        "preferredFullName":"Jacob Bery",
        "region":"IS",
        "phoneNumber":"408-2222222",
        "emailAddress":"Jacob@gmail.com"
    },
    
    {
        "id":"11",
        "jobTitleName":"Frontend Enginer",
        "firstName":"Jamie",
        "lastName":"Butto",
        "preferredFullName":"Jamie Butto",
        "region":"IS",
        "phoneNumber":"408-2222222",
        "emailAddress":"Jamie@gmail.com"
    },

    {
        "id":"12",
        "jobTitleName":"QA Enginer",
        "firstName":"Jessica",
        "lastName":"Dark",
        "preferredFullName":"Jessica Dark",
        "region":"IS",
        "phoneNumber":"408-2222222",
        "emailAddress":"Jessi@gmail.com"
    },

    {
        "id":"13",
        "jobTitleName":"Developer",
        "firstName":"Ava",
        "lastName":"Dark",
        "preferredFullName":"Ava Dark",
        "region":"FR",
        "phoneNumber":"408-2222222",
        "emailAddress":"Ava@gmail.com"
    },

    {
        "id":"14",
        "jobTitleName":"Developer",
        "firstName":"Asher",
        "lastName":"Brown",
        "preferredFullName":"Asher Brown",
        "region":"FR",
        "phoneNumber":"408-2222222",
        "emailAddress":"Asher@gmail.com"
    },
    {
        "id":"15",
        "jobTitleName":"Automation Engineer",
        "firstName":"Amie",
        "lastName":"Jones",
        "preferredFullName":"Amie Jones",
        "region":"FR",
        "phoneNumber":"408-2222222",
        "emailAddress":"Amie@gmail.com"
    },

    {
        "id":"16",
        "jobTitleName":"QA Developer",
        "firstName":"Amelia",
        "lastName":"Obama",
        "preferredFullName":"Amelia Obama",
        "region":"FR",
        "phoneNumber":"408-2222222",
        "emailAddress":"amelia@gmail.com"
    },

    {
        "id":"17",
        "jobTitleName":"QA Developer",
        "firstName":"Amelia",
        "lastName":"Obama",
        "preferredFullName":"Amelia Obama",
        "region":"FR",
        "phoneNumber":"408-2222222",
        "emailAddress":"amelia@gmail.com"
    },
    {
        "id":"18",
        "jobTitleName":"Developer",
        "firstName":"Ellie",
        "lastName":"Obama",
        "preferredFullName":"Ellie Obama",
        "region":"FR",
        "phoneNumber":"408-2245223",
        "emailAddress":"Ellie@gmail.com"
    },
    {
        "id":"19",
        "jobTitleName":"QA Developer",
        "firstName":"Edward",
        "lastName":"Obama",
        "preferredFullName":"Edward Obama",
        "region":"FR",
        "phoneNumber":"408-3312222",
        "emailAddress":"edward@gmail.com"
    },
    {
        "id":"20",
        "jobTitleName":"QA Developer",
        "firstName":"Emma",
        "lastName":"Miller",
        "preferredFullName":"Emma Miller",
        "region":"FR",
        "phoneNumber":"408-2222222",
        "emailAddress":"Emma.12@gmail.com"
    },
    {
        "id":"21",
        "jobTitleName":"DevOps Developer",
        "firstName":"Tommy",
        "lastName":"Miller",
        "preferredFullName":"Tommy Miller",
        "region":"FR",
        "phoneNumber":"408-2222222",
        "emailAddress":"tommy@gmail.com"
    },
    {
        "id":"22",
        "jobTitleName":"C Developer",
        "firstName":"Mia",
        "lastName":"Miller",
        "preferredFullName":"Mia Miller",
        "region":"USA",
        "phoneNumber":"408-2222222",
        "emailAddress":"mia@gmail.com"
    },
    {
        "id":"23",
        "jobTitleName":"Java Developer",
        "firstName":"Daisy",
        "lastName":"Brown",
        "preferredFullName":"Daisy Brown",
        "region":"USA",
        "phoneNumber":"408-2222222",
        "emailAddress":"Daisy@gmail.com"
    },
    {
        "id":"24",
        "jobTitleName":"C++ Developer",
        "firstName":"Danny",
        "lastName":"Davis",
        "preferredFullName":"Danny Davis",
        "region":"FR",
        "phoneNumber":"408-2222222",
        "emailAddress":"Danny_9@gmail.com"
    },
    {
        "id":"25",
        "jobTitleName":"Unity Developer",
        "firstName":"David",
        "lastName":"Garcia",
        "preferredFullName":"David Garcia",
        "region":"USA",
        "phoneNumber":"408-2222222",
        "emailAddress":"David@gmail.com"
    },
    {
        "id":"26",
        "jobTitleName":"product manger",
        "firstName":"Sera",
        "lastName":"Welson",
        "preferredFullName":"Sera Welson",
        "region":"USA",
        "phoneNumber":"048-1114444",
        "emailAddress":"Sera_Welson@gmail.com"
    },
    {
        "id":"27",
        "jobTitleName":"Data Scientiest",
        "firstName":"Joy",
        "lastName":"Garden",
        "preferredFullName":"Joy Garden",
        "region":"WA",
        "phoneNumber":"408-4446622",
        "emailAddress":"Joy.Garden@gmail.com"

    },
    {
        "id":"28",
        "jobTitleName":"Software Developer",
        "firstName":"Liam",
        "lastName":"Smith",
        "preferredFullName":"Liam Smith",
        "region":"TX",
        "phoneNumber":"408-6221569",
        "emailAddress":"Smith-Liam@yahoo.com"
    },
    {
        "id":"29",
        "jobTitleName":"Information Security Analyst",
        "firstName":"Olivia",
        "lastName":"Brown",
        "preferredFullName":"Oliva Brown",
        "region":"FR",
        "phoneNumber":"408-7772210",
        "emailAddress":"brownoliva@outlook.com"
    },
    {
        "id":"30",
        "jobTitleName":"Computer Systems Analyst",
        "firstName":"Elijah",
        "lastName":"Miller",
        "preferredFullName":"Elijah Miller",
        "region":"FR",
        "phoneNumber":"408-8881200",
        "emailAddress":"Elijah.Miller@yandex.com"
    },
    {
        "id":"31",
        "jobTitleName":"Web Developer",
        "firstName":"Charlotte",
        "lastName":"Garcia",
        "preferredFullName":"Charlotte Garcia",
        "region":"KS",
        "phoneNumber":"408-7023153",
        "emailAddress":"Ch12-Ga@yahoo.com"   
    },
    {
        "id":"32",
        "jobTitleName":"Sales Engineer",
        "firstName":"Ava",
        "lastName":"Davis",
        "preferredFullName":"Ava Davis",
        "region":"WY",
        "phoneNumber":"408-2200123",
        "emailAddress":"DAeva@gamil.com"
    },
    {
        "id":"33",
        "jobTitleName":"Information Technology Manager",
        "firstName":"Alexander",
        "lastName":"Jones",
        "preferredFullName":"Alexander Jones",
        "region":"OK",
        "phoneNumber":"408-01522534",
        "emailAddress":"Alexjon@hotmail.com"
    },
    {
        "id":"34",
        "jobTitleName":"Computer Research Scientist",
        "firstName":"Evelyn",
        "lastName":"Williams",
        "preferredFullName":"Evelyn Williams",
        "region":"NY",
        "phoneNumber":"408-5400326",
        "emailAddress":"E1256len@yandex.com"
    },
    {
        "id":"35",
        "jobTitleName":"Marketing Technologist",
        "firstName":"Amelia",
        "lastName":"Johnson",
        "preferredFullName":"Amelia Johnson",
        "region":"MT",
        "phoneNumber":"408-9128051",
        "emailAddress":"Amelia.johan@hotamil.com"
    },
    {
        "id":"36",
        "jobTitleName":"SEO Consultant",
        "firstName":"Sophia",
        "lastName":"Jones",
        "preferredFullName":"Sophia Jones",
        "region":"CA",
        "phoneNumber":"048-9023888",
        "emailAddress":"JONESOPIA@gmail.com"
    },
    {
        "id":"37",
        "jobTitleName":"Web Analytics Developer",
        "firstName":"Isabella",
        "lastName":"Welson",
        "preferredFullName":"Isabella Welson",
        "region":"NE",
        "phoneNumber":"408-4522200",
        "emailAddress":"WEkbella@outlook.com"
    },
    {
        "id":"38",
        "jobTitleName":"Digital Marketing Manger",
        "firstName":"Benjamin",
        "lastName":"Hanks",
        "preferredFullName":"Benjamin Hanks",
        "region":"CA",
        "phoneNumber":"408-6261544",
        "emailAddress":"Benjamin.Hanks@gmail.com"
    },
    {
        "id":"39",
        "jobTitleName":"Social Media Manger",
        "firstName":"James",
        "lastName":"Anderson",
        "preferredFullName":"James Anderson",
        "region":"LA",
        "phoneNumber":"408-3904572",
        "emailAddress":"Anderson_james@hotmail.com"
    },
    {
        "id":"40",
        "jobTitleName":"Content Manger",
        "firstName":"Daisy",
        "lastName":"Yousef",
        "preferredFullName":"Daisy Yousef",
        "region":"LA",
        "phoneNumber":"408-5334122",
        "emailAddress":"D512_Y@outlook.com"
    },
    {
        "id":"41",
        "jobTitleName":"Content Strategsist",
        "firstName":"Henry",
        "lastName":"Perez",
        "preferredFullName":"Henry Perez",
        "region":"NY",
        "phoneNumber":"408-9853333",
        "emailAddress":"PerezHenry@hotmail.com"
    },
    {
        "id":"42",
        "jobTitleName":"Information Architect",
        "firstName":"Harper",
        "lastName":"Clark",
        "preferredFullName":"Harper Clark",
        "region":"MN",
        "phoneNumber":"408-0022452",
        "emailAddress":"Har.co@yandex.com"
    },
    {
        "id":"43",
        "jobTitleName":"UX Designer",
        "firstName":"William",
        "lastName":"Welson",
        "region":"NE",
        "phoneNumber":"408-6645310",
        "emailAddress":"William.wel@hotmail.com"
    },
    {
        "id":"44",
        "jobTitleName":"UI Designer",
        "firstName":"Lucas",
        "lastName":"King",
        "preferredFullName":"Lucas King",
        "region":"LA",
        "phoneNumber":"408-5344011",
        "emailAddress":"King1888@gmail.com"
    },
    {
        "id":"45",
        "jobTitleName":"Accessibility Specialist",
        "firstName":"Evelyn",
        "lastName":"Lewis",
        "preferredFullName":"Evelyn Lewis",
        "region":"WY",
        "phoneNumber":"408-7120000",
        "emailAddress":"EveLW@outlook.com"
    },
    {
        "id":"46",
        "jobTitleName":"Interaction Designer",
        "firstName":"Noah",
        "lastName":"Allen",
        "region":"TX",
        "phoneNumber":"408-6258888",
        "emailAddress":"Noah.Allen@yahoo.com"
    },
    {
        "id":"47",
        "jobTitleName":"Wordpress Developer",
        "firstName":"Liam",
        "lastName":"Taylor",
        "region":"SD",
        "phoneNumber":"408-6534210",
        "emailAddress":"TaylorLiam@hotmail.com"
    },
    {
        "id":"48",
        "jobTitleName":"Framworks Specialist",
        "firstName":"Charlotte",
        "lastName":"Reto",
        "region":"MO",
        "phoneNumber":"408-5344100",
        "emailAddress":"Cha.Re@yahoo.com"
    },
    {
        "id":"49",
        "jobTitleName":"Python Developer",
        "firstName":"Mia",
        "lastName":"Martinez",
        "preferredFullName":"Mia Martinez",
        "region":"OK",
        "phoneNumber":"408-9910055",
        "emailAddress":"MIA4451@gmail.com"
        },
        {
          "id":"50",
          "jobTitleName":"Business System Analyst",
          "firstName":"Alexander",
          "lastName":"Dark",
          "preferredFullName":"Alexander Dark",
          "region":"NY",
          "phoneNumber":"408-7052344",
          "emailAddress":"Darky_Alexa123@hotmail.com"
        }
    ]

    }